{"Band":"50+1050","InputC":"0123456789+","BandC":"0123456789+=abcdefghij_#","Start":"anfang","Empty":"_","Trans":"# Gehe zum Anfang der Zeichenkette\n(anfang, _) --> (anfang, _, R)\n(anfang, {{*}}) -> (sumzei, {{c}}, L)\n\n# Setze das Gleichheitszeichen an Anfang der Zeichenkette\n(sumzei, _) -> (zifprep, =, R)\n\n# Gehe zum Ende der Zeichenkette\n(zifprep, _) --> (zifr, _, L)\n(zifprep, {{*}}) -> (zifprep, {{c}}, R)\n\n# Lade Zeichen auf rechter Seite der Formel\n(zifr, +) --> (zifl, +, L) # Kein Zeichen auf R mehr übrig\n(zifr, {{0-9}}) -> (zifpl{{c}}, {{m:a-j}}, L)\n(zifr, {{*}}) -> (zifr, {{c}}, L)\n\n# Gehe zur linken Seite der Formel\n(zifpl{{v:0-9}}, +) -> (zifl{{v:0}}, +, L)\n(zifpl{{v:0-9}}, {{*}}) -> ({{s}}, {{c}}, L)\n\n# Lade Zeichen auf linker Seite der Formel\n(zifl, =) -> (zifend, {{c}}, R)\n(zifl{{v:0-9}}, =) -> (zife{{v:0}}, {{c}}, L) # Kein Zeichen auf L mehr übrig\n(zifl{{v:0-9}}, {{0-9}}) -> (zifes{{add:0+c}}, {{m:a-j}}, L)\n(zifl{{v:0-9}}, {{*}}) -> ({{s}}, {{c}}, L)\n(zifl, {{0-9}}) -> (zifes{{c}}, {{m:a-j}}, L)\n(zifl, {{*}}) -> (zifl, {{c}}, L)\n\n# Gehe zum Ergebnis\n(zifes{{v:0-9}}{{v:0-9}}, =) -> (zife{{v:0}}{{v:1}}, {{c}}, L)\n(zifes{{v:0-9}}, =) -> (zife{{v:0}}, {{c}}, L)\n(zifes{{v:0-9}}{{v:0-9}}, {{*}}) -> ({{s}}, {{c}}, L)\n(zifes{{v:0-9}}, {{*}}) -> ({{s}}, {{c}}, L)\n\n# Finde Ende des Ergebnisses\n(zife{{v:0-9}}, #) --> (zifeu{{v:0}}, _, R) # Ergebnis hatte Übertrag\n(zife{{v:0-9}}{{v:0-9}}, #) --> (zifeu{{v:0}}{{v:1}}, _, R) # Ergebnis hat Übertrag\n(zife{{v:0-9}}, _) --> (zifprep, {{v:0}}, R) # Ergebnis hat keinen Übertrag\n(zife{{v:0-9}}{{v:0-9}}, _) --> (zifesu{{v:0}}, {{v:1}}, L)\n(zife{{v:0-9}}, {{*}}) --> ({{s}}, {{c}}, L)\n(zife{{v:0-9}}{{v:0-9}}, {{*}}) --> ({{s}}, {{c}}, L)\n\n# Rechnen mit Übertrag\n(zifeu{{v:0-9}}{{v:0-9}}, {{0-9}}) -> (zifeu_{{v:0}}_{{add:1+c}}, {{c}}, L)\n(zifeu{{v:0-9}}, {{0-9}}) -> (zifeu_0_{{add:0+c}}, {{c}}, L)\n(zifeu_{{v:0-9}}_{{v:0-9}}, _) --> (zifeu__{{v:0}}_{{v:1}}, {{c}}, R)\n(zifeu_{{v:0-9}}_{{v:0-9}}{{v:0-9}}, _) --> (zifeu__{{v:0}}_{{v:1}}{{v:2}}, {{c}}, R)\n\n# Rechnen mit Übertrag Schritt 2\n(zifeu__{{v:1-9}}_{{v:0-9}}, {{0-9}}) --> (zifesu{{v:0}}, {{v:1}}, L)\n(zifeu__0_{{v:0-9}}, {{0-9}}) --> (zifprep, {{v:0}}, R)\n(zifeu__{{v:1-9}}_{{v:0-9}}{{v:0-9}}, {{0-9}}) --> (zifeu__{{v:0}}{{v:1}}, {{v:2}}, L)\n(zifeu__0_{{v:0-9}}{{v:0-9}}, {{0-9}}) --> (zifesu{{v:0}}, {{v:1}}, L)\n\n# Markiere Übertrag\n(zifesu{{v:0-9}}, _) -> (zifesu_, {{v:0}}, L)\n(zifesu_, _) -> (zifprep, #, R)\n\n# Ende der Kalkulation\n(zifend, _) --> (zifends, {{c}}, L)\n(zifend, {{*}}) --> (zifend, {{c}}, R)\n(zifends, _#) --> ({{s}}, _, H)\n(zifends, {{a-j}}) -> ({{s}}, {{m:0-9}}, L)\n(zifends, {{*}}) --> ({{s}}, {{c}}, L)","Expert":true}